LICENSE.txt
MANIFEST.in
README
VERSION
contributors.txt
requirements.txt
setup.cfg
setup.py
nekbot/__init__.py
nekbot.plugins.urls.egg-info/PKG-INFO
nekbot.plugins.urls.egg-info/SOURCES.txt
nekbot.plugins.urls.egg-info/dependency_links.txt
nekbot.plugins.urls.egg-info/namespace_packages.txt
nekbot.plugins.urls.egg-info/not-zip-safe
nekbot.plugins.urls.egg-info/requires.txt
nekbot.plugins.urls.egg-info/top_level.txt
nekbot/plugins/__init__.py
nekbot/plugins/urls/__init__.py
nekbot/plugins/urls/generic.py
nekbot/plugins/urls/meneame.py
nekbot/plugins/urls/urlinfo.py
nekbot/plugins/urls/youtube.py