Metadata-Version: 1.1
Name: nekbot.plugins.urls
Version: 0.1.0.1
Summary: urls, a plugin for NekBot, a modular and multiprotocol bot written in Python.
Home-page: http://nekmo.com
Author: Nekmo
Author-email: contacto@nekmo.com
License: UNKNOWN
Keywords: nekbot,bot,urls,plugins,chat
Platform: linux
Provides: nekbot.plugins.urls
